prefect_mcp_server_pkg/__init__.py
prefect_mcp_server_pkg/server.py
iflow_mcp_fortunto2_prefect_mcp_server-1.1.3.dist-info/METADATA
iflow_mcp_fortunto2_prefect_mcp_server-1.1.3.dist-info/WHEEL
iflow_mcp_fortunto2_prefect_mcp_server-1.1.3.dist-info/entry_points.txt
iflow_mcp_fortunto2_prefect_mcp_server-1.1.3.dist-info/licenses/LICENSE
iflow_mcp_fortunto2_prefect_mcp_server-1.1.3.dist-info/RECORD
